tbl2star/.DS_Store
tbl2star/__init__.py
tbl2star/_tools.py
tbl2star/main.py
tbl2star-1.0.1.dist-info/METADATA
tbl2star-1.0.1.dist-info/WHEEL
tbl2star-1.0.1.dist-info/entry_points.txt
tbl2star-1.0.1.dist-info/RECORD
