Metadata-Version: 2.1
Name: tbl2star
Version: 1.0.1
Summary: A tool converting DYNAMO table files(.tbl) to RELION star files(.star)
Home-page: https://github.com/ZhenHuangLab/tbl2star.git
Author: Zhen Huang
Author-email: hzvictor@zju.edu.cn
Requires-Python: >=3.9,<4.0
Classifier: Programming Language :: Python :: 3
Classifier: Programming Language :: Python :: 3.9
Classifier: Programming Language :: Python :: 3.10
Classifier: Programming Language :: Python :: 3.11
Requires-Dist: dynamotable (>=0.2.4,<0.3.0)
Requires-Dist: eulerangles (>=1.0.2,<2.0.0)
Requires-Dist: numpy (>=1.24.2,<2.0.0)
Requires-Dist: pandas (>=1.5.3,<2.0.0)
Requires-Dist: starfile (>=0.4.11,<0.5.0)
Requires-Dist: typer[all] (>=0.7.0,<0.8.0)
Project-URL: Documentation, https://github.com/ZhenHuangLab/tbl2star#readme
Project-URL: Repository, https://github.com/ZhenHuangLab/tbl2star.git
